more.body_model-0.1-py3.5-nspkg.pth
more/body_model/__init__.py
more/body_model/app.py
more/body_model/directive.py
more/body_model/request.py
more/body_model/tests/test_body_model.py
more.body_model-0.1.dist-info/DESCRIPTION.rst
more.body_model-0.1.dist-info/METADATA
more.body_model-0.1.dist-info/RECORD
more.body_model-0.1.dist-info/WHEEL
more.body_model-0.1.dist-info/metadata.json
more.body_model-0.1.dist-info/namespace_packages.txt
more.body_model-0.1.dist-info/top_level.txt
