Metadata-Version: 2.0
Name: more.body-model
Version: 0.1
Summary: load_json infrastructure for Morepath
Home-page: https://github.com/morepath/more.body_model
Author: Henri Hulski
Author-email: henri.hulski@gazeta.pl
License: BSD
Keywords: morepath validation
Platform: UNKNOWN
Classifier: Intended Audience :: Developers
Classifier: License :: OSI Approved :: BSD License
Classifier: Programming Language :: Python :: 2.7
Classifier: Programming Language :: Python :: 3.4
Classifier: Programming Language :: Python :: 3.5
Requires-Dist: morepath (>=0.18)
Provides-Extra: coverage
Requires-Dist: pytest-cov; extra == 'coverage'
Provides-Extra: pep8
Requires-Dist: flake8; extra == 'pep8'
Requires-Dist: pep8-naming; extra == 'pep8'
Provides-Extra: test
Requires-Dist: pytest (>=2.9.1); extra == 'test'
Requires-Dist: pytest-remove-stale-bytecode; extra == 'test'
Requires-Dist: webtest; extra == 'test'
